pose_pipeline/__init__.py
pose_pipeline/env.py
pose_pipeline/paths.py
pose_pipeline/pipeline.py
pose_pipeline/demo/h36_dj.py
pose_pipeline/utils/__init__.py
pose_pipeline/utils/annotation.py
pose_pipeline/utils/bounding_box.py
pose_pipeline/utils/inference.py
pose_pipeline/utils/jupyter.py
pose_pipeline/utils/keypoint_matching.py
pose_pipeline/utils/keypoints.py
pose_pipeline/utils/lifting.py
pose_pipeline/utils/paths.py
pose_pipeline/utils/smpl.py
pose_pipeline/utils/standard_pipelines.py
pose_pipeline/utils/tracking.py
pose_pipeline/utils/video_format.py
pose_pipeline/utils/visualization.py
pose_pipeline/weights/deploy.prototxt
pose_pipeline/weights/res10_300x300_ssd_iter_140000_fp16.caffemodel
pose_pipeline/wrappers/__init__.py
pose_pipeline/wrappers/bridging.py
pose_pipeline/wrappers/centerhmr.py
pose_pipeline/wrappers/expose.py
pose_pipeline/wrappers/facenet.py
pose_pipeline/wrappers/fairmot.py
pose_pipeline/wrappers/gastnet_lifting.py
pose_pipeline/wrappers/hand_bbox.py
pose_pipeline/wrappers/hand_estimation.py
pose_pipeline/wrappers/humor.py
pose_pipeline/wrappers/hybrik.py
pose_pipeline/wrappers/meva.py
pose_pipeline/wrappers/mmaction.py
pose_pipeline/wrappers/mmdet.py
pose_pipeline/wrappers/mmpose.py
pose_pipeline/wrappers/mmtrack.py
pose_pipeline/wrappers/openpose.py
pose_pipeline/wrappers/pare.py
pose_pipeline/wrappers/pixie.py
pose_pipeline/wrappers/poseaug.py
pose_pipeline/wrappers/poseformer.py
pose_pipeline/wrappers/prohmr.py
pose_pipeline/wrappers/rie_lifting.py
pose_pipeline/wrappers/trades.py
pose_pipeline/wrappers/transtrack.py
pose_pipeline/wrappers/vibe.py
pose_pipeline/wrappers/videopose3d.py
pose_pipeline/wrappers/deep_sort_yolov4/LICENSE
pose_pipeline/wrappers/deep_sort_yolov4/README.md
pose_pipeline/wrappers/deep_sort_yolov4/__init__.py
pose_pipeline/wrappers/deep_sort_yolov4/convert.py
pose_pipeline/wrappers/deep_sort_yolov4/parser.py
pose_pipeline/wrappers/deep_sort_yolov4/yolo.py
pose_pipeline-2025.5.2.dist-info/METADATA
pose_pipeline-2025.5.2.dist-info/WHEEL
pose_pipeline-2025.5.2.dist-info/licenses/LICENSE
pose_pipeline-2025.5.2.dist-info/RECORD
