Metadata-Version: 2.4
Name: pose_pipeline
Version: 2025.5.2
Summary: Video pose analysis pipelines for DataJoint.
License-File: LICENSE
Requires-Python: >=3.10
Requires-Dist: datajoint>=0.14.2
Requires-Dist: matplotlib>=3.9.2
Requires-Dist: motmetrics>=1.4.0
Requires-Dist: numpy<2.0.0,>1.24
Requires-Dist: opencv-contrib-python==4.9.0.80
Requires-Dist: opencv-python==4.9.0.80
Requires-Dist: openmim==0.3.9
Requires-Dist: pycocotools==2.0.8
Requires-Dist: pyrender>=0.1.45
Requires-Dist: tensorflow-hub
Requires-Dist: tensorflow[and-cuda]>=2.14.0
Requires-Dist: tf-keras>=2.18.0
Requires-Dist: torch>=2.0.1
Requires-Dist: torchaudio>=2.0.2
Requires-Dist: torchvision>=0.15.2
Provides-Extra: build
Requires-Dist: pip>22; extra == 'build'
Requires-Dist: setuptools>70; extra == 'build'
Provides-Extra: compile
Requires-Dist: chumpy>0.4; extra == 'compile'
Provides-Extra: dev
Requires-Dist: ipympl; extra == 'dev'
Requires-Dist: ipython; extra == 'dev'
Requires-Dist: ipywidgets; extra == 'dev'
Requires-Dist: pytest; extra == 'dev'
Requires-Dist: seaborn; extra == 'dev'
